costctl/__init__.py
costctl/commonfunctions.py
costctl/dsnResolver.py
costctl/heap_dump.py
costctl/jvm_reports.py
costctl/main.py
costctl/removeCelluloid.py
costctl-0.6.dist-info/METADATA
costctl-0.6.dist-info/WHEEL
costctl-0.6.dist-info/entry_points.txt
costctl-0.6.dist-info/top_level.txt
costctl-0.6.dist-info/RECORD
