Metadata-Version: 2.1
Name: costctl
Version: 0.6
Requires-Dist: click
Requires-Dist: rich
